{
  "type": "footer",
  "name": "t:sections.refactor_words.labels.footer_group",
  "sections": {
    "474d772e-c2ad-487c-88bc-ee480cf1399e": {
      "type": "testimonials",
      "blocks": {
        "sections--15155421118537__474d772e-c2ad-487c-88bc-ee480cf1399e-1683007769b0a8fbb7-0": {
          "type": "testimonial",
          "settings": {
            "quote": "",
            "author_name": "",
            "author_title": ""
          }
        },
        "sections--15155421118537__474d772e-c2ad-487c-88bc-ee480cf1399e-1683007769b0a8fbb7-1": {
          "type": "testimonial",
          "disabled": true,
          "settings": {
            "quote": "",
            "author_name": "Author",
            "author_title": "Customer"
          }
        }
      },
      "block_order": [
        "sections--15155421118537__474d772e-c2ad-487c-88bc-ee480cf1399e-1683007769b0a8fbb7-0",
        "sections--15155421118537__474d772e-c2ad-487c-88bc-ee480cf1399e-1683007769b0a8fbb7-1"
      ],
      "settings": {
        "color_bg": "rgba(0,0,0,0)",
        "color_text": "rgba(0,0,0,0)"
      }
    },
    "text-columns-with-icons": {
      "type": "text-columns-with-icons",
      "blocks": {
        "dc0e2351-9175-4503-9568-f4f102cbc798": {
          "type": "text-icon",
          "settings": {
            "title": "Pickup",
            "body": "<p><strong>FREE<\/strong> in-store pickup at our Chippendale flower shop<\/p><p>Monday-Sunday 9am-5pm<\/p>",
            "icon": "earth-globe"
          }
        },
        "00665f2b-5814-4213-853b-3b6c73955a4a": {
          "type": "text-icon",
          "settings": {
            "title": "Delivery",
            "body": "<p>We deliver from 9am-6pm throughout the day.<\/p><p>Pricing is based on distance from our shop.<\/p><p>Check our <a href=\"\/policies\/shipping-policy\" target=\"_blank\" title=\"Shipping Policy\">shipping policy<\/a>.<\/p>",
            "icon": "earth-globe"
          }
        },
        "913a05c0-114a-4fb7-ba39-047df22f46cf": {
          "type": "text-icon",
          "settings": {
            "title": "Returns",
            "body": "<p>If you are unhappy with the quality of your arrangement please email us for replacement within 24 hours.<\/p><p>See our <a href=\"\/policies\/refund-policy\" target=\"_blank\" title=\"Refund Policy\">refund policy<\/a>.<\/p>",
            "icon": "earth-globe"
          }
        }
      },
      "block_order": [
        "dc0e2351-9175-4503-9568-f4f102cbc798",
        "00665f2b-5814-4213-853b-3b6c73955a4a",
        "913a05c0-114a-4fb7-ba39-047df22f46cf"
      ],
      "settings": {
        "text_alignment": "left",
        "color_text": "#262626",
        "color_bg": "#f2f2f2",
        "seo_h_tag": "h3"
      }
    },
    "footer": {
      "type": "footer",
      "blocks": {
        "ba419de3-13f8-4d5e-be47-b93dfa9392fb": {
          "type": "social",
          "settings": {
            "title": ""
          }
        },
        "c8e8f4a6-0e1b-473b-81ca-597ab380f83a": {
          "type": "text",
          "settings": {
            "title": "",
            "content": "<h5><a href=\"\/pages\/faq\" title=\"FAQ\">FAQ<\/a><\/h5><h5><a href=\"https:\/\/www.pastoraleflower.com.au\/pages\/how-to-take-care-your-flowers\" title=\"https:\/\/www.pastoraleflower.com.au\/pages\/how-to-take-care-your-flowers\">Flower Care<\/a><\/h5><h5><a href=\"\/pages\/hi-flower-lover\" title=\"Hi Flower Lover!\">Flower Subscription<\/a><\/h5><h5><a href=\"\/policies\/terms-of-service\" target=\"_blank\" title=\"Terms of Service\">Terms of Service<\/a><\/h5><h5><a href=\"\/policies\/privacy-policy\" target=\"_blank\" title=\"Privacy Policy\">Privacy Policy<\/a><\/h5><p><\/p>",
            "size": ""
          }
        },
        "dd55c003-c48f-495c-9535-b59e9b07d865": {
          "type": "newsletter",
          "settings": {
            "title": "Join Our Blooms!"
          }
        }
      },
      "block_order": [
        "ba419de3-13f8-4d5e-be47-b93dfa9392fb",
        "c8e8f4a6-0e1b-473b-81ca-597ab380f83a",
        "dd55c003-c48f-495c-9535-b59e9b07d865"
      ],
      "settings": {
        "show_payment_icons": true,
        "show_locale_selector": false,
        "show_country_selector": false,
        "seo_h_tag": "h4"
      }
    }
  },
  "order": [
    "474d772e-c2ad-487c-88bc-ee480cf1399e",
    "text-columns-with-icons",
    "footer"
  ]
}
